lins_pix/__init__.py
lins_pix/qrcode.py
lins_pix/settings.py
lins_pix/utils.py
lins_pix/psp/__init__.py
lins_pix/psp/santander/__init__.py
lins_pix/psp/santander/autenticacao.py
lins_pix/psp/santander/cob.py
lins_pix/psp/tests/__init__.py
lins_pix/psp/tests/test_api_santander.py
lins_pix-2.0.8.dist-info/METADATA
lins_pix-2.0.8.dist-info/WHEEL
lins_pix-2.0.8.dist-info/top_level.txt
lins_pix-2.0.8.dist-info/RECORD
