Metadata-Version: 2.1
Name: lins-pix
Version: 2.0.8
Summary: Pacote para gerenciar transacoes PIX
Home-page: https://bitbucket.org/grupolinsferrao/pypck-lins-pix/
Author: Grupo Lins Ferrão
Author-email: ti@grupolinsferrao.com.br
License: MIT
Platform: UNKNOWN
Requires-Dist: qrcode==7.3.1
Requires-Dist: requests==2.27.1
Requires-Dist: PyJWT==1.7.1
Requires-Dist: lins-log==2.1.5.74
Requires-Dist: python-dotenv==1.0.0
